cloudflare_radar/__init__.py
cloudflare_radar/cmds/__init__.py
cloudflare_radar/cmds/ranking.py
cloudflare_radar/utils/__init__.py
cloudflare_radar/utils/attribute.py
cloudflare_radar/utils/domains.py
cloudflare_radar/utils/ranking.py
cloudflare_radar/utils/request.py
cloudflare_radar-0.3.dist-info/LICENSE
cloudflare_radar-0.3.dist-info/METADATA
cloudflare_radar-0.3.dist-info/WHEEL
cloudflare_radar-0.3.dist-info/entry_points.txt
cloudflare_radar-0.3.dist-info/top_level.txt
cloudflare_radar-0.3.dist-info/zip-safe
cloudflare_radar-0.3.dist-info/RECORD
