Metadata-Version: 2.1
Name: cloudflare-radar
Version: 0.3
Summary: Get data from https://radar.cloudflare.com
Home-page: https://github.com/DNSet/cloudflare-radar/
Author: Mingzhe Zou
Author-email: zoumingzhe@outlook.com
License: GPLv2
Project-URL: Source Code, https://github.com/DNSet/cloudflare-radar/
Project-URL: Bug Tracker, https://github.com/DNSet/cloudflare-radar/issues
Project-URL: Documentation, https://github.com/DNSet/cloudflare-radar/
Platform: any
Classifier: Programming Language :: Python
Classifier: Programming Language :: Python :: 3
Requires-Python: >=3.8
License-File: LICENSE
Requires-Dist: xarg-python >=1.3.3
Requires-Dist: requests >=2.31.0
Requires-Dist: pycountry
